odoo/addons/base_external_system/README.rst
odoo/addons/base_external_system/__init__.py
odoo/addons/base_external_system/__manifest__.py
odoo/addons/base_external_system/demo/external_system_os_demo.xml
odoo/addons/base_external_system/i18n/base_external_system.pot
odoo/addons/base_external_system/i18n/es.po
odoo/addons/base_external_system/i18n/it.po
odoo/addons/base_external_system/models/__init__.py
odoo/addons/base_external_system/models/external_system.py
odoo/addons/base_external_system/models/external_system_adapter.py
odoo/addons/base_external_system/models/external_system_os.py
odoo/addons/base_external_system/readme/CONFIGURE.rst
odoo/addons/base_external_system/readme/CONTRIBUTORS.rst
odoo/addons/base_external_system/readme/DESCRIPTION.rst
odoo/addons/base_external_system/readme/USAGE.rst
odoo/addons/base_external_system/security/ir.model.access.csv
odoo/addons/base_external_system/static/description/icon.png
odoo/addons/base_external_system/static/description/index.html
odoo/addons/base_external_system/tests/__init__.py
odoo/addons/base_external_system/tests/common.py
odoo/addons/base_external_system/tests/test_external_system.py
odoo/addons/base_external_system/tests/test_external_system_adapter.py
odoo/addons/base_external_system/tests/test_external_system_os.py
odoo/addons/base_external_system/views/external_system_view.xml
odoo_addon_base_external_system-16.0.1.0.0.7.dist-info/METADATA
odoo_addon_base_external_system-16.0.1.0.0.7.dist-info/WHEEL
odoo_addon_base_external_system-16.0.1.0.0.7.dist-info/top_level.txt
odoo_addon_base_external_system-16.0.1.0.0.7.dist-info/RECORD
